entity_recognition_lib/EntityRecognizer.py
entity_recognition_lib/__init__.py
entity_recognition_lib/data/tech_entities.json
entity_recognition_lib/functions/__init__.py
entity_recognition_lib/functions/entity_extraction.py
entity_recognition_lib/functions/recommendation_generation.py
entity_recognition_lib/functions/topic_classification.py
entity_recognition_lib/models.py
entity_recognition_lib/utils.py
entity_recognition_lib-0.1.6.dist-info/LICENSE
entity_recognition_lib-0.1.6.dist-info/METADATA
entity_recognition_lib-0.1.6.dist-info/WHEEL
entity_recognition_lib-0.1.6.dist-info/RECORD
