Metadata-Version: 2.1
Name: entity-recognition-lib
Version: 0.1.6
Summary: A library for technology entity recognition and recommendation
License: MIT
Author: Cesar Goncalves
Author-email: goncalves.cesaraugusto94@gmail.com
Requires-Python: >=3.11,<4.0
Classifier: License :: OSI Approved :: MIT License
Classifier: Programming Language :: Python :: 3
Classifier: Programming Language :: Python :: 3.11
Classifier: Programming Language :: Python :: 3.12
Requires-Dist: aiofiles (>=23.2.1,<24.0.0)
Requires-Dist: bertopic (==0.16.1)
Requires-Dist: hdbscan (>=0.8.33,<0.9.0)
Requires-Dist: numpy (>=1.26.4,<2.0.0)
Requires-Dist: pandas (>=2.2.2,<3.0.0)
Requires-Dist: scikit-learn (>=1.4.2,<2.0.0)
Requires-Dist: scipy (>=1.13.0,<2.0.0)
Requires-Dist: spacy (>=3.7.4,<4.0.0)
Requires-Dist: torch (>=2.2.2,<3.0.0)
Requires-Dist: transformers (>=4.40.0,<5.0.0)
